pt4cloud/__init__.py
pt4cloud/lite.py
pt4cloud/pt4cloud.py
pt4cloud-0.3.1.dist-info/METADATA
pt4cloud-0.3.1.dist-info/WHEEL
pt4cloud-0.3.1.dist-info/RECORD
