Metadata-Version: 2.1
Name: pt4cloud
Version: 0.3.1
Summary: Python implementation of PT4Cloud as descibed by He et al. https://doi.org/10.1145/3338906.3338912
Author: Fabian
Author-email: 1803fabian@gmail.com
Requires-Python: >=3.10,<4.0
Classifier: Programming Language :: Python :: 3
Classifier: Programming Language :: Python :: 3.10
Classifier: Programming Language :: Python :: 3.11
Classifier: Programming Language :: Python :: 3.12
Classifier: Programming Language :: Python :: 3.13
Requires-Dist: numpy (>=2.1.3,<3.0.0)
Requires-Dist: scipy (>=1.14.1,<2.0.0)
